JasurOmanov/__init__.py
JasurOmanov/core.py
JasurOmanov/download.py
jasuromanov-0.0.7.dist-info/licenses/LICENSE
jasuromanov-0.0.7.dist-info/METADATA
jasuromanov-0.0.7.dist-info/WHEEL
jasuromanov-0.0.7.dist-info/top_level.txt
jasuromanov-0.0.7.dist-info/RECORD
