Metadata-Version: 2.4
Name: JasurOmanov
Version: 0.0.7
Summary: Oddiy kutubxona
Author: Jasur Omanov
Author-email: jasuromanov05@gmail.com
License: MIT
Classifier: Programming Language :: Python :: 3
Classifier: License :: OSI Approved :: MIT License
Requires-Python: >=3.6
License-File: LICENSE
Dynamic: author
Dynamic: author-email
Dynamic: classifier
Dynamic: description
Dynamic: description-content-type
Dynamic: license
Dynamic: license-file
Dynamic: requires-python
Dynamic: summary
